odoo_driver/__init__.py
odoo_driver/app.py
odoo_driver/cli.py
odoo_driver/default_cert/server.crt
odoo_driver/default_cert/server.key
odoo_driver/devices/__init__.py
odoo_driver/devices/device_display.py
odoo_driver/devices/device_payment.py
odoo_driver/devices/device_printer.py
odoo_driver/devices/device_scale.py
odoo_driver/devices/models/__init__.py
odoo_driver/devices/models/device_abstract.py
odoo_driver/devices/models/device_abstract_with_queue.py
odoo_driver/devices/models/device_task.py
odoo_driver/devices/scale_dialog06/__init__.py
odoo_driver/devices/scale_dialog06/scale_answer.py
odoo_driver/devices/scale_dialog06/scale_command.py
odoo_driver/devices/scale_dialog06/state_machine.py
odoo_driver/devices/tools/__init__.py
odoo_driver/devices/tools/serial_code.py
odoo_driver/flask_app/__init__.py
odoo_driver/flask_app/flask_app_display.py
odoo_driver/flask_app/flask_app_odoo.py
odoo_driver/flask_app/flask_app_payment.py
odoo_driver/flask_app/flask_app_printer.py
odoo_driver/flask_app/flask_app_scale.py
odoo_driver/flask_app/flask_app_website.py
odoo_driver/interface.py
odoo_driver/static/audio/photo-taken.wav
odoo_driver/static/css/bootstrap.min.css
odoo_driver/static/css/bootstrap.min.css.map
odoo_driver/static/css/odoo_pos_driver.css
odoo_driver/static/devices/display.png
odoo_driver/static/devices/display__aures__ocd_300.png
odoo_driver/static/devices/display__oxhoo__af240.png
odoo_driver/static/devices/payment.png
odoo_driver/static/devices/payment__ingenico__desk_5000.png
odoo_driver/static/devices/payment__ingenico__move_5000.png
odoo_driver/static/devices/printer.png
odoo_driver/static/devices/printer__epson__tm_t20.png
odoo_driver/static/devices/printer__epson__tm_t88.png
odoo_driver/static/devices/scale.png
odoo_driver/static/devices/scale__mettler_toledo__ariva_s.png
odoo_driver/static/img/favicon.png
odoo_driver/static/img/odoo.png
odoo_driver/static/js/bootstrap.min.js
odoo_driver/static/js/bootstrap.min.js.map
odoo_driver/static/js/jquery.min.js
odoo_driver-0.10.0.dist-info/METADATA
odoo_driver-0.10.0.dist-info/WHEEL
odoo_driver-0.10.0.dist-info/entry_points.txt
odoo_driver-0.10.0.dist-info/RECORD
