Metadata-Version: 2.4
Name: odoo-driver
Version: 0.10.0
Summary:     Python library to communicates with devices used by Odoo.(Mainly Point of Sale application)Alternative to Iot Box Odoo solution or Pywebdriver community solution.
License: AGPLv3+
Keywords: Odoo,Point Of Sale,Driver
Author: Sylvain LE GAL
Author-email: sylvain.legal@grap.coop
Maintainer: Sylvain LE GAL
Maintainer-email: sylvain.legal@grap.coop
Requires-Python: >=3.9,<4.0
Classifier: License :: OSI Approved :: GNU Affero General Public License v3 or later (AGPLv3+)
Classifier: Intended Audience :: Developers
Classifier: Development Status :: 4 - Beta
Classifier: Operating System :: Unix
Classifier: Programming Language :: Python :: 3.9
Classifier: Programming Language :: Python :: 3.10
Classifier: Programming Language :: Python :: 3.11
Classifier: Programming Language :: Python :: 3.12
Classifier: Programming Language :: Python :: 3.13
Classifier: Programming Language :: Python :: 3.14
Classifier: Framework :: Odoo
Requires-Dist: click-loglevel
Requires-Dist: flask
Requires-Dist: flask-babel
Requires-Dist: flask-cors
Requires-Dist: gevent
Requires-Dist: gevent-websocket
Requires-Dist: importlib-resources
Requires-Dist: loguru
Requires-Dist: psutil
Requires-Dist: pyserial
Requires-Dist: pyteliummanager
Requires-Dist: python-escpos
Requires-Dist: python-statemachine
Requires-Dist: pyusb
Requires-Dist: simplejson
Requires-Dist: single-source
Requires-Dist: unidecode
Project-URL: Repository, https://gitlab.com/grap-rhone-alpes/odoo-driver
